<?xml version="1.0" encoding="utf-8" ?>
<c2layout>
    <name>Login</name>
    <sid>333729672408571</sid>
    <event-sheet>LoginEvents</event-sheet>
    <size>
        <width>1280</width>
        <height>1024</height>
    </size>
    <margins>
        <horizontal>500</horizontal>
        <vertical>500</vertical>
    </margins>
    <unbounded-scrolling>0</unbounded-scrolling>
    <layers>
        <layer name="Background" sid="816341556619529">
            <initially-visible>1</initially-visible>
            <background-color>255,255,255</background-color>
            <transparent>0</transparent>
            <parallax>
                <x>1</x>
                <y>1</y>
            </parallax>
            <zoom-rate>1</zoom-rate>
            <opacity>1</opacity>
            <force-own-texture>0</force-own-texture>
            <global>0</global>
            <use-render-cells>0</use-render-cells>
            <blend-mode>0</blend-mode>
            <effect-fallback>0</effect-fallback>
            <instances />
            <effects />
        </layer>
        <layer name="UI" sid="767250198934046">
            <initially-visible>1</initially-visible>
            <background-color>255,255,255</background-color>
            <transparent>1</transparent>
            <parallax>
                <x>1</x>
                <y>1</y>
            </parallax>
            <zoom-rate>1</zoom-rate>
            <opacity>1</opacity>
            <force-own-texture>0</force-own-texture>
            <global>0</global>
            <use-render-cells>0</use-render-cells>
            <blend-mode>0</blend-mode>
            <effect-fallback>0</effect-fallback>
            <instances>
                <instance type="TiledBackground" uid="16">
                    <properties>
                        <initial-visibility>Visible</initial-visibility>
                        <hotspot>Top-left</hotspot>
                    </properties>
                    <blend-mode>0</blend-mode>
                    <effect-fallback>0</effect-fallback>
                    <world>
                        <x>0</x>
                        <y>0</y>
                        <z>0</z>
                        <width>1280</width>
                        <height>1024</height>
                        <depth>0</depth>
                        <hotspotX>0</hotspotX>
                        <hotspotY>0</hotspotY>
                        <angle>0</angle>
                        <opacity>1</opacity>
                    </world>
                </instance>
                <instance type="LoginTitle" uid="17">
                    <properties>
                        <text>Spacewar tribute</text>
                        <initial-visibility>Visible</initial-visibility>
                        <font>Arial,-64,400,0</font>
                        <color>255,255,255</color>
                        <horizontal-alignment>Center</horizontal-alignment>
                        <vertical-alignment>Bottom</vertical-alignment>
                        <hotspot>Top-left</hotspot>
                        <wrapping>Word</wrapping>
                        <line-height>0</line-height>
                    </properties>
                    <blend-mode>0</blend-mode>
                    <effect-fallback>0</effect-fallback>
                    <world>
                        <x>61</x>
                        <y>219</y>
                        <z>0</z>
                        <width>1168</width>
                        <height>229</height>
                        <depth>0</depth>
                        <hotspotX>0</hotspotX>
                        <hotspotY>0</hotspotY>
                        <angle>0</angle>
                        <opacity>1</opacity>
                    </world>
                </instance>
                <instance type="NameLabel" uid="21">
                    <properties>
                        <text>Nick:</text>
                        <initial-visibility>Visible</initial-visibility>
                        <font>Arial,-37,400,0</font>
                        <color>255,255,255</color>
                        <horizontal-alignment>Right</horizontal-alignment>
                        <vertical-alignment>Top</vertical-alignment>
                        <hotspot>Top-left</hotspot>
                        <wrapping>Word</wrapping>
                        <line-height>0</line-height>
                    </properties>
                    <blend-mode>0</blend-mode>
                    <effect-fallback>0</effect-fallback>
                    <world>
                        <x>47</x>
                        <y>493</y>
                        <z>0</z>
                        <width>297</width>
                        <height>113</height>
                        <depth>0</depth>
                        <hotspotX>0</hotspotX>
                        <hotspotY>0</hotspotY>
                        <angle>0</angle>
                        <opacity>1</opacity>
                    </world>
                </instance>
                <instance type="NameTextBox" uid="22">
                    <properties>
                        <text></text>
                        <placeholder></placeholder>
                        <tooltip></tooltip>
                        <initial-visibility>Visible</initial-visibility>
                        <enabled>Yes</enabled>
                        <read-only>No</read-only>
                        <spell-check>No</spell-check>
                        <type>Text</type>
                        <auto-font-size>Yes</auto-font-size>
                        <id-optional></id-optional>
                    </properties>
                    <blend-mode>0</blend-mode>
                    <effect-fallback>0</effect-fallback>
                    <world>
                        <x>362</x>
                        <y>488</y>
                        <z>0</z>
                        <width>586</width>
                        <height>52</height>
                        <depth>0</depth>
                        <hotspotX>0</hotspotX>
                        <hotspotY>0</hotspotY>
                    </world>
                </instance>
                <instance type="JoinButton" uid="23">
                    <properties>
                        <type>Button</type>
                        <text>Play</text>
                        <tooltip></tooltip>
                        <initial-visibility>Visible</initial-visibility>
                        <enabled>Yes</enabled>
                        <auto-font-size>Yes</auto-font-size>
                        <id-optional></id-optional>
                        <checked>No</checked>
                    </properties>
                    <blend-mode>0</blend-mode>
                    <effect-fallback>0</effect-fallback>
                    <world>
                        <x>975</x>
                        <y>488</y>
                        <z>0</z>
                        <width>120</width>
                        <height>52</height>
                        <depth>0</depth>
                        <hotspotX>0</hotspotX>
                        <hotspotY>0</hotspotY>
                    </world>
                </instance>
                <instance type="TipsLabel" uid="24">
                    <properties>
                        <text>Tips:</text>
                        <initial-visibility>Visible</initial-visibility>
                        <font>Arial,-48,400,0</font>
                        <color>255,255,255</color>
                        <horizontal-alignment>Center</horizontal-alignment>
                        <vertical-alignment>Center</vertical-alignment>
                        <hotspot>Center</hotspot>
                        <wrapping>Word</wrapping>
                        <line-height>0</line-height>
                    </properties>
                    <blend-mode>0</blend-mode>
                    <effect-fallback>0</effect-fallback>
                    <world>
                        <x>641</x>
                        <y>608</y>
                        <z>0</z>
                        <width>1191</width>
                        <height>70</height>
                        <depth>0</depth>
                        <hotspotX>0.5</hotspotX>
                        <hotspotY>0.5</hotspotY>
                        <angle>0</angle>
                        <opacity>1</opacity>
                    </world>
                </instance>
                <instance type="TipsLabel2" uid="25">
                    <properties>
                        <text>Aim &amp; shot with mouse, space to accelerate</text>
                        <initial-visibility>Visible</initial-visibility>
                        <font>Arial,-35,400,0</font>
                        <color>255,255,255</color>
                        <horizontal-alignment>Center</horizontal-alignment>
                        <vertical-alignment>Top</vertical-alignment>
                        <hotspot>Top-left</hotspot>
                        <wrapping>Word</wrapping>
                        <line-height>0</line-height>
                    </properties>
                    <blend-mode>0</blend-mode>
                    <effect-fallback>0</effect-fallback>
                    <world>
                        <x>52</x>
                        <y>644</y>
                        <z>0</z>
                        <width>1172</width>
                        <height>339</height>
                        <depth>0</depth>
                        <hotspotX>0</hotspotX>
                        <hotspotY>0</hotspotY>
                        <angle>0</angle>
                        <opacity>1</opacity>
                    </world>
                </instance>
            </instances>
            <effects />
        </layer>
    </layers>
    <nonworld-instances />
    <effects />
</c2layout>
